setup.py
deTiN/__about__.py
deTiN/__init__.py
deTiN/deTiN.py
deTiN/deTiN_SSNV_based_estimate.py
deTiN/deTiN_aSCNA_based_estimate.py
deTiN/deTiN_utilities.py
deTiN.egg-info/PKG-INFO
deTiN.egg-info/SOURCES.txt
deTiN.egg-info/dependency_links.txt
deTiN.egg-info/entry_points.txt
deTiN.egg-info/requires.txt
deTiN.egg-info/top_level.txt