Metadata-Version: 1.1
Name: deTiN
Version: 1.7.5.3
Summary: Somatic analysis toolkit for dealing with tumor in normal contamination
Home-page: UNKNOWN
Author: Broad Institute - Cancer Genome Computational Analysis
Author-email: amaro@broadinstitute.org
License: UNKNOWN
Platform: UNKNOWN
Classifier: Programming Language :: Python :: 2
Classifier: Intended Audience :: Science/Research
Classifier: Topic :: Scientific/Engineering :: Bio-Informatics
